multi_ruptures/__init__.py
multi_ruptures/api/__init__.py
multi_ruptures/api/pettitt.py
multi_ruptures/api/rpt.py
multi_ruptures/api/stat.py
multi_ruptures/core/__init__.py
multi_ruptures/viz/__init__.py
multi_ruptures/viz/plot.py
multi_ruptures-0.1.3.dist-info/LICENSE
multi_ruptures-0.1.3.dist-info/METADATA
multi_ruptures-0.1.3.dist-info/WHEEL
multi_ruptures-0.1.3.dist-info/RECORD
