Metadata-Version: 2.1
Name: multi-ruptures
Version: 0.1.3
Summary: Multiple breakpoint detection toolkit.
License: MIT
Author: SongshGeo
Author-email: songshgeo@gmail.com
Requires-Python: >=3.8.1,<3.12
Classifier: License :: OSI Approved :: MIT License
Classifier: Programming Language :: Python :: 3
Classifier: Programming Language :: Python :: 3.9
Classifier: Programming Language :: Python :: 3.10
Classifier: Programming Language :: Python :: 3.11
Requires-Dist: future-annotations (>=1.0.0)
Requires-Dist: hydra-core (>=1.3)
Requires-Dist: matplotkit (>=0.1.2)
Requires-Dist: pandas (>=2)
Requires-Dist: pyhomogeneity (>=1.1)
Requires-Dist: ruptures (>=1.1.9)
Requires-Dist: typing-extensions (>=4.12.2)
